LICENSE
setup.py
ifhist/__init__.py
ifhist/ifstat.py
ifhist.egg-info/PKG-INFO
ifhist.egg-info/SOURCES.txt
ifhist.egg-info/dependency_links.txt
ifhist.egg-info/entry_points.txt
ifhist.egg-info/top_level.txt