Metadata-Version: 1.1
Name: ifhist
Version: 0.1.dev
Summary: Gather usage statistics for network interfaces.
Home-page: https://fixedpoint.nl/svn/ifstat
Author: Jeroen F.J. Laros
Author-email: jlaros@fixedpoint.nl
License: MIT License
Keywords: network interface stats
Platform: any
Classifier: Development Status :: 3 - Alpha
Classifier: Environment :: Console
Classifier: Intended Audience :: System Administrators
Classifier: Operating System :: OS Independent
Classifier: Programming Language :: Python
Classifier: Topic :: System :: Networking :: Monitoring
